workbook_api/__init__.py
workbook_api/workbook_api.py
workbook_api-0.0.11.dist-info/METADATA
workbook_api-0.0.11.dist-info/WHEEL
workbook_api-0.0.11.dist-info/top_level.txt
workbook_api-0.0.11.dist-info/RECORD
