Metadata-Version: 2.1
Name: workbook-api
Version: 0.0.11
Summary: A wrapper for the API for workbook.net
Home-page: https://github.com/tobiasbp/workbook-api
Author: Tobias Balle-Petersen
Author-email: tobiasbp@gmail.com
License: MIT
Keywords: Workbook api wrapper client
Platform: UNKNOWN
Classifier: Programming Language :: Python :: 3
Classifier: License :: OSI Approved :: MIT License
Classifier: Operating System :: OS Independent
Requires-Python: >=3.5
Requires-Dist: requests
